itunes_last_export/__init__.py
itunes_last_export/db_management.py
itunes_last_export/gui.py
itunes_last_export/server_management.py
itunes_last_export/update_playcount.py
itunes_last_export-0.0.6.dist-info/METADATA
itunes_last_export-0.0.6.dist-info/RECORD
itunes_last_export-0.0.6.dist-info/WHEEL
itunes_last_export-0.0.6.dist-info/entry_points.txt
itunes_last_export-0.0.6.dist-info/top_level.txt
