Metadata-Version: 2.1
Name: itunes-last-export
Version: 0.0.6
Summary: Tool to import playcounts and loved tracks from your last.fm account into iTunes
Home-page: https://github.com/werdeil/itunes-last-export
Author: Vincent Verdeil
Author-email: vincent.verdeil@gmail.com
License: GPLv3
Keywords: iTunes,Last.fm,scrobble
Platform: UNKNOWN
Classifier: Development Status :: 4 - Beta
Classifier: Environment :: MacOS X
Classifier: Intended Audience :: Developers
Classifier: Intended Audience :: End Users/Desktop
Classifier: License :: OSI Approved :: GNU General Public License v3 (GPLv3)
Classifier: Programming Language :: Python
Classifier: Topic :: Multimedia :: Sound/Audio
Requires-Dist: requests
